pyrecodes/__init__.py
pyrecodes/constants.py
pyrecodes/main.py
pyrecodes/utilities.py
pyrecodes/component/__init__.py
pyrecodes/component/building_with_emergency_calls.py
pyrecodes/component/component.py
pyrecodes/component/infrastructure_interface.py
pyrecodes/component/r2d_component.py
pyrecodes/component/standard_irecodes_component.py
pyrecodes/component_configurator/__init__.py
pyrecodes/component_configurator/component_configurator.py
pyrecodes/component_configurator/r2d_component_configurator.py
pyrecodes/component_configurator/r2d_dict_getter.py
pyrecodes/component_configurator/r2d_repair_configurator.py
pyrecodes/component_configurator/repair_configurator.py
pyrecodes/component_configurator/tier1_interface_configurator.py
pyrecodes/component_library_creator/__init__.py
pyrecodes/component_library_creator/component_library_creator.py
pyrecodes/component_library_creator/json_component_library_creator.py
pyrecodes/component_recovery_model/__init__.py
pyrecodes/component_recovery_model/abstract_recovery_model.py
pyrecodes/component_recovery_model/component_level_recovery_activities_model.py
pyrecodes/component_recovery_model/concrete_recovery_activity.py
pyrecodes/component_recovery_model/infrastructure_interface_recovery_model.py
pyrecodes/component_recovery_model/no_recovery_activity_model.py
pyrecodes/component_recovery_model/recovery_activity.py
pyrecodes/component_recovery_model/recovery_model.py
pyrecodes/damage_input/__init__.py
pyrecodes/damage_input/damage_input.py
pyrecodes/damage_input/file_damage_input.py
pyrecodes/damage_input/list_damage_input.py
pyrecodes/damage_input/r2d_damage_input.py
pyrecodes/distribution_priority/__init__.py
pyrecodes/distribution_priority/component_based_priority.py
pyrecodes/distribution_priority/component_type_priority.py
pyrecodes/distribution_priority/distribution_priority.py
pyrecodes/distribution_priority/random_priority.py
pyrecodes/distribution_priority/random_priority_with_prioritized_interfaces.py
pyrecodes-0.2.0.dist-info/LICENSE
pyrecodes-0.2.0.dist-info/METADATA
pyrecodes-0.2.0.dist-info/WHEEL
pyrecodes-0.2.0.dist-info/top_level.txt
pyrecodes-0.2.0.dist-info/RECORD
