Metadata-Version: 2.2
Name: pyrecodes
Version: 0.2.0
Summary: Software for Regional Recovery Modelling and Resilience Assessment of the Built Environment
Home-page: https://github.com/NikolaBlagojevic/pyrecodes
Author: Nikola Blagojevic and Bozidar Stojadinovic
Author-email: nikolab@stanford.edu
Requires-Python: >=3.9
License-File: LICENSE
Requires-Dist: absl-py==2.1.0
Requires-Dist: affine==2.4.0
Requires-Dist: alabaster==0.7.16
Requires-Dist: appnope==0.1.4
Requires-Dist: asttokens==3.0.0
Requires-Dist: attrs==24.3.0
Requires-Dist: babel==2.16.0
Requires-Dist: beautifulsoup4==4.12.3
Requires-Dist: blosc2==2.5.1
Requires-Dist: BRAILS==3.1.3
Requires-Dist: certifi==2024.12.14
Requires-Dist: charset-normalizer==3.4.1
Requires-Dist: click==8.1.8
Requires-Dist: click-plugins==1.1.1
Requires-Dist: cligj==0.7.2
Requires-Dist: comm==0.2.2
Requires-Dist: contextily==1.6.2
Requires-Dist: contourpy==1.3.0
Requires-Dist: coverage==7.6.10
Requires-Dist: cycler==0.12.1
Requires-Dist: debugpy==1.8.11
Requires-Dist: decorator==5.1.1
Requires-Dist: dill==0.3.9
Requires-Dist: docutils==0.21.2
Requires-Dist: et_xmlfile==2.0.0
Requires-Dist: exceptiongroup==1.2.2
Requires-Dist: executing==2.1.0
Requires-Dist: filelock==3.16.1
Requires-Dist: fiona==1.10.1
Requires-Dist: fonttools==4.55.3
Requires-Dist: fsspec==2024.12.0
Requires-Dist: furo==2024.8.6
Requires-Dist: geographiclib==2.0
Requires-Dist: geopandas==1.0.1
Requires-Dist: geopy==2.4.1
Requires-Dist: grpcio==1.69.0
Requires-Dist: huggingface-hub==0.27.1
Requires-Dist: idna==3.10
Requires-Dist: imageio==2.36.1
Requires-Dist: imagesize==1.4.1
Requires-Dist: importlib_metadata==8.5.0
Requires-Dist: importlib_resources==6.4.5
Requires-Dist: iniconfig==2.0.0
Requires-Dist: ipykernel==6.29.5
Requires-Dist: ipython==8.18.1
Requires-Dist: jedi==0.19.2
Requires-Dist: Jinja2==3.1.5
Requires-Dist: joblib==1.4.2
Requires-Dist: jupyter_client==8.6.3
Requires-Dist: jupyter_core==5.7.2
Requires-Dist: kiwisolver==1.4.7
Requires-Dist: libpysal==4.8.1
Requires-Dist: Markdown==3.7
Requires-Dist: MarkupSafe==3.0.2
Requires-Dist: matplotlib==3.9.4
Requires-Dist: matplotlib-inline==0.1.7
Requires-Dist: mercantile==1.2.1
Requires-Dist: momepy==0.6.0
Requires-Dist: mpmath==1.3.0
Requires-Dist: msgpack==1.1.0
Requires-Dist: ndindex==1.9.2
Requires-Dist: nest-asyncio==1.6.0
Requires-Dist: networkx==3.2.1
Requires-Dist: numexpr==2.10.2
Requires-Dist: numpy==1.26.4
Requires-Dist: opencv-python==4.9.0.80
Requires-Dist: openpyxl==3.1.5
Requires-Dist: packaging==24.2
Requires-Dist: pandana==0.7
Requires-Dist: pandas==2.2.3
Requires-Dist: parso==0.8.4
Requires-Dist: pexpect==4.9.0
Requires-Dist: pillow==11.0.0
Requires-Dist: platformdirs==4.3.6
Requires-Dist: pluggy==1.5.0
Requires-Dist: prompt_toolkit==3.0.48
Requires-Dist: protobuf==5.29.3
Requires-Dist: psutil==6.1.1
Requires-Dist: ptyprocess==0.7.0
Requires-Dist: pure_eval==0.2.3
Requires-Dist: py-cpuinfo==9.0.0
Requires-Dist: Pygments==2.18.0
Requires-Dist: pyogrio==0.10.0
Requires-Dist: pyparsing==3.2.0
Requires-Dist: pyproj==3.6.1
Requires-Dist: pytest==8.3.4
Requires-Dist: pytest-cov==6.0.0
Requires-Dist: python-dateutil==2.9.0.post0
Requires-Dist: pytz==2024.2
Requires-Dist: PyYAML==6.0.2
Requires-Dist: pyzmq==26.2.0
Requires-Dist: rasterio==1.4.3
Requires-Dist: regex==2024.11.6
Requires-Dist: requests==2.32.3
Requires-Dist: rewet==0.2.0b11
Requires-Dist: safetensors==0.5.2
Requires-Dist: scikit-learn==1.6.0
Requires-Dist: scipy==1.13.1
Requires-Dist: seaborn==0.13.2
Requires-Dist: shapely==2.0.6
Requires-Dist: six==1.17.0
Requires-Dist: snowballstemmer==2.2.0
Requires-Dist: soupsieve==2.6
Requires-Dist: Sphinx==7.4.7
Requires-Dist: sphinx-basic-ng==1.0.0b2
Requires-Dist: sphinx-carousel==1.2.0
Requires-Dist: sphinx-togglebutton==0.3.2
Requires-Dist: sphinxcontrib-applehelp==2.0.0
Requires-Dist: sphinxcontrib-devhelp==2.0.0
Requires-Dist: sphinxcontrib-htmlhelp==2.1.0
Requires-Dist: sphinxcontrib-jsmath==1.0.1
Requires-Dist: sphinxcontrib-qthelp==2.0.0
Requires-Dist: sphinxcontrib-serializinghtml==2.0.0
Requires-Dist: sphinxcontrib-youtube==1.4.1
Requires-Dist: stack-data==0.6.3
Requires-Dist: sympy==1.13.3
Requires-Dist: tables==3.9.2
Requires-Dist: tensorboard==2.18.0
Requires-Dist: tensorboard-data-server==0.7.2
Requires-Dist: tensorboardX==2.6.2.2
Requires-Dist: threadpoolctl==3.5.0
Requires-Dist: tokenizers==0.21.0
Requires-Dist: tomli==2.2.1
Requires-Dist: torch==2.2.2
Requires-Dist: torchvision==0.17.2
Requires-Dist: tornado==6.4.2
Requires-Dist: tqdm==4.67.1
Requires-Dist: traitlets==5.14.3
Requires-Dist: transformers==4.48.0
Requires-Dist: typing_extensions==4.12.2
Requires-Dist: tzdata==2024.2
Requires-Dist: urllib3==2.3.0
Requires-Dist: wcwidth==0.2.13
Requires-Dist: webcolors==24.11.1
Requires-Dist: Werkzeug==3.1.3
Requires-Dist: wget==3.2
Requires-Dist: wntrfr==1.1.0.1.2
Requires-Dist: xyzservices==2024.9.0
Requires-Dist: yacs==0.1.8
Requires-Dist: zipp==3.21.0
Dynamic: author
Dynamic: author-email
Dynamic: home-page
Dynamic: requires-dist
Dynamic: requires-python
Dynamic: summary
